BiologyTools/CytoplasmicCirculation.py
BiologyTools/Genetics.py
BiologyTools/__init__.py
BiologyTools/define.py
BiologyTools/tools.py
BiologyTools/model/不错.pt
BiologyTools/model/优秀.pt
BiologyTools-0.2.2.dist-info/LICENSE
BiologyTools-0.2.2.dist-info/METADATA
BiologyTools-0.2.2.dist-info/WHEEL
BiologyTools-0.2.2.dist-info/entry_points.txt
BiologyTools-0.2.2.dist-info/top_level.txt
BiologyTools-0.2.2.dist-info/RECORD
