Metadata-Version: 2.1
Name: BiologyTools
Version: 0.2.2
Summary: CrossDark's biology tool
Home-page: https://github.com/CrossDark/BiologyTools
Author: CrossDark
Author-email: liuhanbo333@icloud.com
Classifier: Programming Language :: Python :: 3.11
Classifier: Programming Language :: Python :: 3.12
Classifier: License :: OSI Approved :: MIT License
Classifier: Operating System :: OS Independent
License-File: LICENSE
Requires-Dist: numpy
Requires-Dist: moviepy
Requires-Dist: av
Requires-Dist: ultralytics
Requires-Dist: pymysql
